django_trap/__init__.py
django_trap/admin.py
django_trap/forms.py
django_trap/models.py
django_trap/signals.py
django_trap/urls.py
django_trap/views.py
django_trap/migrations/0001_initial.py
django_trap/migrations/__init__.py
django_trap/templates/django_trap/login.html
django_trap-0.5.0.dist-info/DESCRIPTION.rst
django_trap-0.5.0.dist-info/METADATA
django_trap-0.5.0.dist-info/metadata.json
django_trap-0.5.0.dist-info/RECORD
django_trap-0.5.0.dist-info/top_level.txt
django_trap-0.5.0.dist-info/WHEEL
test/__init__.py
test/settings.py
test/test_suite.py
test/urls.py
