Metadata-Version: 2.0
Name: django-trap
Version: 0.5.0
Summary: A fake Django admin login screen to notify admins of attempted unauthorized access.
Home-page: https://github.com/mvasilkov/django-trap
Author: Mark Vasilkov
Author-email: mvasilkov@gmail.com
License: MIT License
Download-URL: https://github.com/mvasilkov/django-trap/tarball/v0.5.0
Keywords: django admin honeypot trap
Platform: UNKNOWN
Classifier: Development Status :: 5 - Production/Stable
Classifier: Framework :: Django
Classifier: Intended Audience :: Developers
Classifier: License :: OSI Approved :: MIT License
Classifier: Natural Language :: English
Classifier: Operating System :: OS Independent
Classifier: Programming Language :: Python
Classifier: Programming Language :: Python :: 2
Classifier: Programming Language :: Python :: 2.6
Classifier: Programming Language :: Python :: 2.7
Classifier: Programming Language :: Python :: 3
Classifier: Programming Language :: Python :: 3.2
Classifier: Programming Language :: Python :: 3.3
Classifier: Topic :: Internet :: WWW/HTTP :: Dynamic Content
